gdmec2310199/__init__.py
gdmec2310199-0.1.4.dist-info/METADATA
gdmec2310199-0.1.4.dist-info/WHEEL
gdmec2310199-0.1.4.dist-info/entry_points.txt
gdmec2310199-0.1.4.dist-info/RECORD
